pyPolyMesher/__init__.py
pyPolyMesher/dFunctions.py
pyPolyMesher/dxfImporter.py
pyPolyMesher/exampleDomains.py
pyPolyMesher/progress.py
pyPolyMesher/pyPolyMesher.py
PolyMesher-1.1.dist-info/LICENSE
PolyMesher-1.1.dist-info/METADATA
PolyMesher-1.1.dist-info/WHEEL
PolyMesher-1.1.dist-info/top_level.txt
PolyMesher-1.1.dist-info/RECORD
