Metadata-Version: 2.1
Name: PolyMesher
Version: 1.1
Summary: A Python package for polygonal mesh generation
Home-page: https://github.com/Sad-Abd/pyPolyMesher
Author: Sad-Abd
Author-email: abedisadjad@gmail.com
License: GPL-3.0
Classifier: Programming Language :: Python :: 3
Classifier: Intended Audience :: Science/Research
Classifier: Topic :: Scientific/Engineering :: Mathematics
Classifier: Topic :: Scientific/Engineering
Classifier: License :: OSI Approved :: GNU General Public License v3 (GPLv3)
Classifier: Programming Language :: Python :: 3.8
Classifier: Programming Language :: Python :: 3.9
Classifier: Programming Language :: Python :: 3.10
Classifier: Programming Language :: Python :: 3.11
License-File: LICENSE
Requires-Dist: numpy
Requires-Dist: scipy
Requires-Dist: matplotlib
Requires-Dist: ezdxf
